[
 {
  "allow_in_quick_entry": 0,
  "allow_on_submit": 0,
  "bold": 0,
  "collapsible": 0,
  "collapsible_depends_on": null,
  "columns": 0,
  "default": "0",
  "depends_on": null,
  "description": null,
  "docstatus": 0,
  "doctype": "Custom Field",
  "dt": "Journal Entry",
  "fetch_from": null,
  "fetch_if_empty": 0,
  "fieldname": "custom_is_vat_entry",
  "fieldtype": "Check",
  "hidden": 0,
  "hide_border": 0,
  "hide_days": 0,
  "hide_seconds": 0,
  "ignore_user_permissions": 0,
  "ignore_xss_filter": 0,
  "in_global_search": 0,
  "in_list_view": 0,
  "in_preview": 0,
  "in_standard_filter": 0,
  "insert_after": "voucher_type",
  "is_system_generated": 0,
  "is_virtual": 0,
  "label": "Is VAT Entry",
  "length": 0,
  "link_filters": null,
  "mandatory_depends_on": null,
  "modified": "2025-05-09 12:46:52.554257",
  "module": null,
  "name": "Journal Entry-custom_is_vat_entry",
  "no_copy": 0,
  "non_negative": 0,
  "options": null,
  "permlevel": 0,
  "placeholder": null,
  "precision": "",
  "print_hide": 0,
  "print_hide_if_no_value": 0,
  "print_width": null,
  "read_only": 0,
  "read_only_depends_on": null,
  "report_hide": 0,
  "reqd": 0,
  "search_index": 0,
  "show_dashboard": 0,
  "sort_options": 0,
  "translatable": 0,
  "unique": 0,
  "width": null
 },
 {
  "allow_in_quick_entry": 0,
  "allow_on_submit": 0,
  "bold": 0,
  "collapsible": 0,
  "collapsible_depends_on": null,
  "columns": 0,
  "default": null,
  "depends_on": null,
  "description": null,
  "docstatus": 0,
  "doctype": "Custom Field",
  "dt": "Journal Entry",
  "fetch_from": null,
  "fetch_if_empty": 0,
  "fieldname": "custom_section_break_zce99",
  "fieldtype": "Section Break",
  "hidden": 0,
  "hide_border": 0,
  "hide_days": 0,
  "hide_seconds": 0,
  "ignore_user_permissions": 0,
  "ignore_xss_filter": 0,
  "in_global_search": 0,
  "in_list_view": 0,
  "in_preview": 0,
  "in_standard_filter": 0,
  "insert_after": "apply_tds",
  "is_system_generated": 0,
  "is_virtual": 0,
  "label": "",
  "length": 0,
  "link_filters": null,
  "mandatory_depends_on": null,
  "modified": "2025-03-19 21:17:36.943996",
  "module": null,
  "name": "Journal Entry-custom_section_break_zce99",
  "no_copy": 0,
  "non_negative": 0,
  "options": null,
  "permlevel": 0,
  "placeholder": null,
  "precision": "",
  "print_hide": 0,
  "print_hide_if_no_value": 0,
  "print_width": null,
  "read_only": 0,
  "read_only_depends_on": null,
  "report_hide": 0,
  "reqd": 0,
  "search_index": 0,
  "show_dashboard": 0,
  "sort_options": 0,
  "translatable": 0,
  "unique": 0,
  "width": null
 },
 {
  "allow_in_quick_entry": 0,
  "allow_on_submit": 0,
  "bold": 0,
  "collapsible": 0,
  "collapsible_depends_on": null,
  "columns": 0,
  "default": null,
  "depends_on": null,
  "description": null,
  "docstatus": 0,
  "doctype": "Custom Field",
  "dt": "Journal Entry",
  "fetch_from": null,
  "fetch_if_empty": 0,
  "fieldname": "custom_supplier_namecashbank_purchase",
  "fieldtype": "Data",
  "hidden": 0,
  "hide_border": 0,
  "hide_days": 0,
  "hide_seconds": 0,
  "ignore_user_permissions": 0,
  "ignore_xss_filter": 0,
  "in_global_search": 0,
  "in_list_view": 0,
  "in_preview": 0,
  "in_standard_filter": 0,
  "insert_after": "custom_section_break_zce99",
  "is_system_generated": 0,
  "is_virtual": 0,
  "label": "Supplier Name(Cash/Bank Purchase)",
  "length": 0,
  "link_filters": null,
  "mandatory_depends_on": null,
  "modified": "2025-03-19 21:13:19.884999",
  "module": null,
  "name": "Journal Entry-custom_supplier_namecashbank_purchase",
  "no_copy": 0,
  "non_negative": 0,
  "options": null,
  "permlevel": 0,
  "placeholder": null,
  "precision": "",
  "print_hide": 0,
  "print_hide_if_no_value": 0,
  "print_width": null,
  "read_only": 0,
  "read_only_depends_on": null,
  "report_hide": 0,
  "reqd": 0,
  "search_index": 0,
  "show_dashboard": 0,
  "sort_options": 0,
  "translatable": 1,
  "unique": 0,
  "width": null
 },
 {
  "allow_in_quick_entry": 0,
  "allow_on_submit": 0,
  "bold": 0,
  "collapsible": 0,
  "collapsible_depends_on": null,
  "columns": 0,
  "default": null,
  "depends_on": null,
  "description": null,
  "docstatus": 0,
  "doctype": "Custom Field",
  "dt": "Journal Entry",
  "fetch_from": null,
  "fetch_if_empty": 0,
  "fieldname": "custom_column_break_fy95c",
  "fieldtype": "Column Break",
  "hidden": 0,
  "hide_border": 0,
  "hide_days": 0,
  "hide_seconds": 0,
  "ignore_user_permissions": 0,
  "ignore_xss_filter": 0,
  "in_global_search": 0,
  "in_list_view": 0,
  "in_preview": 0,
  "in_standard_filter": 0,
  "insert_after": "custom_supplier_namecashbank_purchase",
  "is_system_generated": 0,
  "is_virtual": 0,
  "label": "",
  "length": 0,
  "link_filters": null,
  "mandatory_depends_on": null,
  "modified": "2025-03-19 21:17:37.106055",
  "module": null,
  "name": "Journal Entry-custom_column_break_fy95c",
  "no_copy": 0,
  "non_negative": 0,
  "options": null,
  "permlevel": 0,
  "placeholder": null,
  "precision": "",
  "print_hide": 0,
  "print_hide_if_no_value": 0,
  "print_width": null,
  "read_only": 0,
  "read_only_depends_on": null,
  "report_hide": 0,
  "reqd": 0,
  "search_index": 0,
  "show_dashboard": 0,
  "sort_options": 0,
  "translatable": 0,
  "unique": 0,
  "width": null
 },
 {
  "allow_in_quick_entry": 0,
  "allow_on_submit": 0,
  "bold": 0,
  "collapsible": 0,
  "collapsible_depends_on": null,
  "columns": 0,
  "default": null,
  "depends_on": null,
  "description": null,
  "docstatus": 0,
  "doctype": "Custom Field",
  "dt": "Journal Entry",
  "fetch_from": null,
  "fetch_if_empty": 0,
  "fieldname": "custom_supplier_invoice_date",
  "fieldtype": "Date",
  "hidden": 0,
  "hide_border": 0,
  "hide_days": 0,
  "hide_seconds": 0,
  "ignore_user_permissions": 0,
  "ignore_xss_filter": 0,
  "in_global_search": 0,
  "in_list_view": 0,
  "in_preview": 0,
  "in_standard_filter": 0,
  "insert_after": "custom_column_break_fy95c",
  "is_system_generated": 0,
  "is_virtual": 0,
  "label": "Supplier Invoice Date",
  "length": 0,
  "link_filters": null,
  "mandatory_depends_on": null,
  "modified": "2025-03-19 21:17:37.245930",
  "module": null,
  "name": "Journal Entry-custom_supplier_invoice_date",
  "no_copy": 0,
  "non_negative": 0,
  "options": null,
  "permlevel": 0,
  "placeholder": null,
  "precision": "",
  "print_hide": 0,
  "print_hide_if_no_value": 0,
  "print_width": null,
  "read_only": 0,
  "read_only_depends_on": null,
  "report_hide": 0,
  "reqd": 0,
  "search_index": 0,
  "show_dashboard": 0,
  "sort_options": 0,
  "translatable": 0,
  "unique": 0,
  "width": null
 },
 {
  "allow_in_quick_entry": 0,
  "allow_on_submit": 0,
  "bold": 0,
  "collapsible": 0,
  "collapsible_depends_on": null,
  "columns": 0,
  "default": null,
  "depends_on": null,
  "description": null,
  "docstatus": 0,
  "doctype": "Custom Field",
  "dt": "Journal Entry",
  "fetch_from": null,
  "fetch_if_empty": 0,
  "fieldname": "custom_column_break_ijdaj",
  "fieldtype": "Column Break",
  "hidden": 0,
  "hide_border": 0,
  "hide_days": 0,
  "hide_seconds": 0,
  "ignore_user_permissions": 0,
  "ignore_xss_filter": 0,
  "in_global_search": 0,
  "in_list_view": 0,
  "in_preview": 0,
  "in_standard_filter": 0,
  "insert_after": "custom_supplier_invoice_date",
  "is_system_generated": 0,
  "is_virtual": 0,
  "label": "",
  "length": 0,
  "link_filters": null,
  "mandatory_depends_on": null,
  "modified": "2025-03-19 21:17:37.401787",
  "module": null,
  "name": "Journal Entry-custom_column_break_ijdaj",
  "no_copy": 0,
  "non_negative": 0,
  "options": null,
  "permlevel": 0,
  "placeholder": null,
  "precision": "",
  "print_hide": 0,
  "print_hide_if_no_value": 0,
  "print_width": null,
  "read_only": 0,
  "read_only_depends_on": null,
  "report_hide": 0,
  "reqd": 0,
  "search_index": 0,
  "show_dashboard": 0,
  "sort_options": 0,
  "translatable": 0,
  "unique": 0,
  "width": null
 },
 {
  "allow_in_quick_entry": 0,
  "allow_on_submit": 0,
  "bold": 0,
  "collapsible": 0,
  "collapsible_depends_on": null,
  "columns": 0,
  "default": null,
  "depends_on": null,
  "description": null,
  "docstatus": 0,
  "doctype": "Custom Field",
  "dt": "Journal Entry",
  "fetch_from": null,
  "fetch_if_empty": 0,
  "fieldname": "custom_vat_no",
  "fieldtype": "Data",
  "hidden": 0,
  "hide_border": 0,
  "hide_days": 0,
  "hide_seconds": 0,
  "ignore_user_permissions": 0,
  "ignore_xss_filter": 0,
  "in_global_search": 0,
  "in_list_view": 0,
  "in_preview": 0,
  "in_standard_filter": 0,
  "insert_after": "custom_column_break_ijdaj",
  "is_system_generated": 0,
  "is_virtual": 0,
  "label": "Vat No.",
  "length": 0,
  "link_filters": null,
  "mandatory_depends_on": null,
  "modified": "2025-03-19 21:13:20.042933",
  "module": null,
  "name": "Journal Entry-custom_vat_no",
  "no_copy": 0,
  "non_negative": 0,
  "options": null,
  "permlevel": 0,
  "placeholder": null,
  "precision": "",
  "print_hide": 0,
  "print_hide_if_no_value": 0,
  "print_width": null,
  "read_only": 0,
  "read_only_depends_on": null,
  "report_hide": 0,
  "reqd": 0,
  "search_index": 0,
  "show_dashboard": 0,
  "sort_options": 0,
  "translatable": 1,
  "unique": 0,
  "width": null
 },
 {
  "allow_in_quick_entry": 0,
  "allow_on_submit": 1,
  "bold": 0,
  "collapsible": 0,
  "collapsible_depends_on": null,
  "columns": 0,
  "default": null,
  "depends_on": null,
  "description": null,
  "docstatus": 0,
  "doctype": "Custom Field",
  "dt": "Journal Entry Account",
  "fetch_from": null,
  "fetch_if_empty": 0,
  "fieldname": "custom_entry_type",
  "fieldtype": "Select",
  "hidden": 0,
  "hide_border": 0,
  "hide_days": 0,
  "hide_seconds": 0,
  "ignore_user_permissions": 0,
  "ignore_xss_filter": 0,
  "in_global_search": 0,
  "in_list_view": 1,
  "in_preview": 0,
  "in_standard_filter": 0,
  "insert_after": "credit_in_account_currency",
  "is_system_generated": 0,
  "is_virtual": 0,
  "label": "Entry Type",
  "length": 0,
  "link_filters": null,
  "mandatory_depends_on": null,
  "modified": "2025-05-09 12:58:05.773871",
  "module": null,
  "name": "Journal Entry Account-custom_entry_type",
  "no_copy": 0,
  "non_negative": 0,
  "options": "\nTaxable Amount\nTax Amount",
  "permlevel": 0,
  "placeholder": null,
  "precision": "",
  "print_hide": 0,
  "print_hide_if_no_value": 0,
  "print_width": null,
  "read_only": 0,
  "read_only_depends_on": null,
  "report_hide": 0,
  "reqd": 0,
  "search_index": 0,
  "show_dashboard": 0,
  "sort_options": 0,
  "translatable": 0,
  "unique": 0,
  "width": null
 }
]